{"frames": [

{
	"filename": "color0_Infantry_Large_face0_0",
	"frame": {"x":1,"y":1,"w":40,"h":58},
	"rotated": false,
	"trimmed": true,
	"spriteSourceSize": {"x":28,"y":36,"w":40,"h":58},
	"sourceSize": {"w":88,"h":108}
},
{
	"filename": "color0_Infantry_Large_face0_1",
	"frame": {"x":1,"y":61,"w":40,"h":58},
	"rotated": false,
	"trimmed": true,
	"spriteSourceSize": {"x":28,"y":36,"w":40,"h":58},
	"sourceSize": {"w":88,"h":108}
},
{
	"filename": "color0_Infantry_Large_face0_2",
	"frame": {"x":1,"y":121,"w":40,"h":58},
	"rotated": false,
	"trimmed": true,
	"spriteSourceSize": {"x":28,"y":36,"w":40,"h":58},
	"sourceSize": {"w":88,"h":108}
},
{
	"filename": "color0_Infantry_Large_face0_3",
	"frame": {"x":1,"y":181,"w":40,"h":58},
	"rotated": false,
	"trimmed": true,
	"spriteSourceSize": {"x":28,"y":36,"w":40,"h":58},
	"sourceSize": {"w":88,"h":108}
},
{
	"filename": "color0_Infantry_Large_face1_0",
	"frame": {"x":1,"y":241,"w":40,"h":58},
	"rotated": false,
	"trimmed": true,
	"spriteSourceSize": {"x":24,"y":36,"w":40,"h":58},
	"sourceSize": {"w":88,"h":108}
},
{
	"filename": "color0_Infantry_Large_face1_1",
	"frame": {"x":1,"y":301,"w":40,"h":58},
	"rotated": false,
	"trimmed": true,
	"spriteSourceSize": {"x":24,"y":36,"w":40,"h":58},
	"sourceSize": {"w":88,"h":108}
},
{
	"filename": "color0_Infantry_Large_face1_2",
	"frame": {"x":1,"y":361,"w":40,"h":58},
	"rotated": false,
	"trimmed": true,
	"spriteSourceSize": {"x":24,"y":36,"w":40,"h":58},
	"sourceSize": {"w":88,"h":108}
},
{
	"filename": "color0_Infantry_Large_face1_3",
	"frame": {"x":1,"y":421,"w":40,"h":58},
	"rotated": false,
	"trimmed": true,
	"spriteSourceSize": {"x":24,"y":36,"w":40,"h":58},
	"sourceSize": {"w":88,"h":108}
},
{
	"filename": "color0_Infantry_Large_face2_0",
	"frame": {"x":1,"y":481,"w":40,"h":56},
	"rotated": false,
	"trimmed": true,
	"spriteSourceSize": {"x":24,"y":36,"w":40,"h":56},
	"sourceSize": {"w":88,"h":108}
},
{
	"filename": "color0_Infantry_Large_face2_1",
	"frame": {"x":1,"y":539,"w":40,"h":56},
	"rotated": false,
	"trimmed": true,
	"spriteSourceSize": {"x":24,"y":36,"w":40,"h":56},
	"sourceSize": {"w":88,"h":108}
},
{
	"filename": "color0_Infantry_Large_face2_2",
	"frame": {"x":1,"y":597,"w":40,"h":56},
	"rotated": false,
	"trimmed": true,
	"spriteSourceSize": {"x":24,"y":36,"w":40,"h":56},
	"sourceSize": {"w":88,"h":108}
},
{
	"filename": "color0_Infantry_Large_face2_3",
	"frame": {"x":1,"y":655,"w":40,"h":56},
	"rotated": false,
	"trimmed": true,
	"spriteSourceSize": {"x":24,"y":36,"w":40,"h":56},
	"sourceSize": {"w":88,"h":108}
},
{
	"filename": "color0_Infantry_Large_face3_0",
	"frame": {"x":1,"y":713,"w":40,"h":56},
	"rotated": false,
	"trimmed": true,
	"spriteSourceSize": {"x":28,"y":36,"w":40,"h":56},
	"sourceSize": {"w":88,"h":108}
},
{
	"filename": "color0_Infantry_Large_face3_1",
	"frame": {"x":1,"y":771,"w":40,"h":56},
	"rotated": false,
	"trimmed": true,
	"spriteSourceSize": {"x":28,"y":36,"w":40,"h":56},
	"sourceSize": {"w":88,"h":108}
},
{
	"filename": "color0_Infantry_Large_face3_2",
	"frame": {"x":1,"y":829,"w":40,"h":56},
	"rotated": false,
	"trimmed": true,
	"spriteSourceSize": {"x":28,"y":36,"w":40,"h":56},
	"sourceSize": {"w":88,"h":108}
},
{
	"filename": "color0_Infantry_Large_face3_3",
	"frame": {"x":1,"y":887,"w":40,"h":56},
	"rotated": false,
	"trimmed": true,
	"spriteSourceSize": {"x":28,"y":36,"w":40,"h":56},
	"sourceSize": {"w":88,"h":108}
}],
"meta": {
	"app": "https://www.codeandweb.com/texturepacker",
	"version": "1.0",
	"image": "standing.png",
	"format": "RGBA8888",
	"size": {"w":42,"h":944},
	"scale": "1",
	"smartupdate": "$TexturePacker:SmartUpdate:6ac8036893e549b4bd14706f919309de:bde607b06818c1f67691472fc4e56fe7:2ee97642ccc49e0a9a6de0b14d52efec$"
}
}
